disjointset/__init__.py
disjointset/__init__.pyi
disjointset/disjointset.py
disjointset/disjointset.pyi
disjointsetunion-1.0.0.dist-info/METADATA
disjointsetunion-1.0.0.dist-info/WHEEL
disjointsetunion-1.0.0.dist-info/top_level.txt
disjointsetunion-1.0.0.dist-info/RECORD
