Metadata-Version: 2.4
Name: disjointsetunion
Version: 1.0.0
Summary: Disjoint Set - Data Structure Implementation
Author-email: CRISvsGAME <cris@crisvsgame.com>
Maintainer-email: CRISvsGAME <cris@crisvsgame.com>
License-Expression: MIT
Project-URL: Repository, https://github.com/CRISvsGAME/disjointset.git
Keywords: disjoint set,data structure,union find
Classifier: Development Status :: 5 - Production/Stable
Classifier: Intended Audience :: Developers
Classifier: Operating System :: OS Independent
Classifier: Programming Language :: Python
Classifier: Topic :: Scientific/Engineering
Classifier: Topic :: Software Development :: Libraries
Requires-Python: >=3.12
Provides-Extra: dev
Requires-Dist: build; extra == "dev"
Requires-Dist: mypy; extra == "dev"
Requires-Dist: pylint; extra == "dev"
Requires-Dist: pytest; extra == "dev"
Requires-Dist: twine; extra == "dev"
